{
    "profiles": [
        {
            "complex_modifications": {
                "parameters": {
                    "basic.to_if_alone_timeout_milliseconds": 800,
                    "basic.to_if_held_down_threshold_milliseconds": 100
                },
                "rules": [
                    {
                        "description": "Map Tab to Hyper when held",
                        "manipulators": [
                            {
                                "from": {
                                    "key_code": "tab",
                                    "modifiers": {
                                        "optional": [
                                            "any"
                                        ]
                                    }
                                },
                                "to": [
                                    {
                                        "key_code": "left_shift",
                                        "modifiers": [
                                            "left_control",
                                            "left_option"
                                        ]
                                    }
                                ],
                                "to_if_alone": [
                                    {
                                        "key_code": "tab"
                                    }
                                ],
                                "type": "basic"
                            }
                        ]
                    },
                    {
                        "description": "Tap Caps Lock for ESC or Hold for Control",
                        "manipulators": [
                            {
                                "from": {
                                    "key_code": "caps_lock",
                                    "modifiers": {
                                        "optional": [
                                            "any"
                                        ]
                                    }
                                },
                                "to": [
                                    {
                                        "key_code": "left_control"
                                    }
                                ],
                                "to_if_alone": [
                                    {
                                        "key_code": "escape"
                                    }
                                ],
                                "conditions": [
                                    {
                                        "type": "frontmost_application_unless",
                                        "bundle_identifiers": [
                                            "^com\\.factorio$"
                                        ],
                                        "file_paths": [
                                            "/Users/seb/Library/Application Support/Steam/steamapps/common/Factorio/factorio.app/Contents/MacOS/factorio$"
                                        ]
                                    }
                                ],
                                "type": "basic"
                            },
                            {
                                "from": {
                                    "key_code": "caps_lock",
                                    "modifiers": {
                                        "optional": [
                                            "any"
                                        ]
                                    }
                                },
                                "to": [
                                    {
                                        "key_code": "left_control",
                                        "lazy": true
                                    }
                                ],
                                "conditions": [
                                    {
                                        "type": "frontmost_application_if",
                                        "bundle_identifiers": [
                                            "^com\\.factorio$"
                                        ],
                                        "file_paths": [
                                            "/Users/seb/Library/Application Support/Steam/steamapps/common/Factorio/factorio.app/Contents/MacOS/factorio$"
                                        ]
                                    }
                                ],
                                "type": "basic"
                            }
                        ]
                    },
                    {
                        "description": "HHKB left_control: tap Escape, hold Control",
                        "manipulators": [
                            {
                                "type": "basic",
                                "from": {
                                    "key_code": "left_control",
                                    "modifiers": {
                                        "optional": [
                                            "any"
                                        ]
                                    }
                                },
                                "to_if_alone": [
                                    {
                                        "key_code": "escape"
                                    }
                                ],
                                "to_if_held_down": [
                                    {
                                        "key_code": "left_control",
                                        "lazy": true
                                    }
                                ],
                                "conditions": [
                                    {
                                        "type": "frontmost_application_unless",
                                        "bundle_identifiers": [
                                            "^com\\.factorio$"
                                        ],
                                        "file_paths": [
                                            "/Users/seb/Library/Application Support/Steam/steamapps/common/Factorio/factorio.app/Contents/MacOS/factorio$"
                                        ]
                                    },
                                    {
                                        "type": "device_if",
                                        "identifiers": [
                                            {
                                                "vendor_id": 1278,
                                                "product_id": 33,
                                                "is_keyboard": true
                                            }
                                        ]
                                    }
                                ]
                            },
                            {
                                "type": "basic",
                                "from": {
                                    "key_code": "left_control",
                                    "modifiers": {
                                        "optional": [
                                            "any"
                                        ]
                                    }
                                },
                                "to": [
                                    {
                                        "key_code": "left_control",
                                        "lazy": true
                                    }
                                ],
                                "conditions": [
                                    {
                                        "type": "frontmost_application_if",
                                        "bundle_identifiers": [
                                            "^com\\.factorio$"
                                        ],
                                        "file_paths": [
                                            "/Users/seb/Library/Application Support/Steam/steamapps/common/Factorio/factorio.app/Contents/MacOS/factorio$"
                                        ]
                                    },
                                    {
                                        "type": "device_if",
                                        "identifiers": [
                                            {
                                                "vendor_id": 1278,
                                                "product_id": 33,
                                                "is_keyboard": true
                                            }
                                        ]
                                    }
                                ]
                            }
                        ]
                    }
                ]
            },
            "devices": [
                {
                    "identifiers": {
                        "is_keyboard": true,
                        "is_pointing_device": true,
                        "product_id": 45915,
                        "vendor_id": 1133
                    },
                    "ignore": false
                },
                {
                    "identifiers": {
                        "is_keyboard": true,
                        "is_pointing_device": true,
                        "product_id": 288,
                        "vendor_id": 13364
                    },
                    "ignore_vendor_events": true
                },
                {
                    "identifiers": {
                        "is_keyboard": true,
                        "product_id": 288,
                        "vendor_id": 13364
                    },
                    "ignore_vendor_events": true
                }
            ],
            "name": "Default profile",
            "selected": true,
            "virtual_hid_keyboard": {
                "keyboard_type_v2": "ansi"
            }
        }
    ]
}
